human_dates/__init__.py
human_dates/from_human.py
human_dates/to_human.py
human_dates/utils.py
human_dates2-1.2.0.dist-info/METADATA
human_dates2-1.2.0.dist-info/WHEEL
human_dates2-1.2.0.dist-info/top_level.txt
human_dates2-1.2.0.dist-info/RECORD
