Metadata-Version: 2.1
Name: human-dates2
Version: 1.2.0
Summary: Dates for humans
Home-page: https://github.com/AleCandido/human_dates
Author: Alessandro Candido
Author-email: candido.ale@gmail.com
License: UNKNOWN
Project-URL: Original SO, http://stackoverflow.com/a/1551394/192791
Project-URL: Original Package, https://pypi.org/project/human_dates/
Keywords: datetime pretty-print human-readable
Platform: UNKNOWN
Classifier: Development Status :: 2 - Pre-Alpha
Classifier: License :: OSI Approved :: MIT License
Classifier: Programming Language :: Python :: 3
Classifier: Programming Language :: Python :: 3.8
Requires-Python: >=3.6
